fastabc/__init__.py
fastabc/baseclasses.py
fastabc/structures.py
fastabc-0.2.3.dist-info/METADATA
fastabc-0.2.3.dist-info/WHEEL
fastabc-0.2.3.dist-info/entry_points.txt
fastabc-0.2.3.dist-info/RECORD
